pynodejs/__init__.py
pynodejs/__main__.py
PyNodeJS-1.0.dist-info/LICENCE.txt
PyNodeJS-1.0.dist-info/METADATA
PyNodeJS-1.0.dist-info/WHEEL
PyNodeJS-1.0.dist-info/top_level.txt
PyNodeJS-1.0.dist-info/RECORD
